pydyno/__init__.py
pydyno/adapters/__init__.py
pydyno/adapters/postgresql.py
pydyno/core/__init__.py
pydyno/core/adapters.py
pydyno/core/exceptions.py
pydyno/core/manager.py
pydyno/core/pool_config.py
pydyno/core/utils.py
pydyno/scripts/__init__.py
pydyno/scripts/test_postgres_adapter.py
pydyno/scripts/test_pydyno_basic.py
pydyno_pool-0.1.3.dist-info/METADATA
pydyno_pool-0.1.3.dist-info/WHEEL
pydyno_pool-0.1.3.dist-info/licenses/LICENSE
pydyno_pool-0.1.3.dist-info/RECORD
