Metadata-Version: 2.4
Name: pydyno_pool
Version: 0.1.3
Summary: A simple pool connection manager based off of Netflix's Dyno package, but for Python
Project-URL: Homepage, https://github.com/ryancraigdavis/PyDyno
Project-URL: Issues, https://github.com/ryancraigdavis/PyDyno/issues
Author-email: Ryan Davis <ryancraigdavis@gmail.com>
License-Expression: MIT
License-File: LICENSE
Keywords: async,connection-pooling,database,netflix-dyno,postgresql,sqlalchemy
Classifier: Development Status :: 3 - Alpha
Classifier: Framework :: AsyncIO
Classifier: Intended Audience :: Developers
Classifier: License :: OSI Approved :: MIT License
Classifier: Operating System :: OS Independent
Classifier: Programming Language :: Python :: 3
Classifier: Programming Language :: Python :: 3.12
Classifier: Programming Language :: Python :: 3.13
Classifier: Topic :: Database
Classifier: Topic :: Software Development :: Libraries :: Python Modules
Requires-Python: >=3.12
Requires-Dist: asyncpg>=0.30.0
Requires-Dist: attrs>=25.3.0
Requires-Dist: sqlalchemy>=2.0.41
Provides-Extra: dependencies
Requires-Dist: asyncpg>=0.30.0; extra == 'dependencies'
Requires-Dist: attrs>=25.3.0; extra == 'dependencies'
Requires-Dist: sqlalchemy>=2.0.41; extra == 'dependencies'
